pytest_chinesereport/__init__.py
pytest_chinesereport/pytest_chinesereport.py
pytest_chinesereport/templates/__init__.py
pytest_chinesereport/templates/templates.html
pytest_chinesereport/templates/templates2.html
pytest_chinesereport-1.0.7.dist-info/LICENSE
pytest_chinesereport-1.0.7.dist-info/METADATA
pytest_chinesereport-1.0.7.dist-info/WHEEL
pytest_chinesereport-1.0.7.dist-info/entry_points.txt
pytest_chinesereport-1.0.7.dist-info/top_level.txt
pytest_chinesereport-1.0.7.dist-info/RECORD
